g3/__init__.py
g3/config/__init__.py
g3/config/exclude.py
g3/config/handler.py
g3/config/log.py
g3/config/openai.py
g3/domain/__init__.py
g3/domain/message_tone.py
g3/initializers/__init__.py
g3/initializers/log.py
g3/main.py
g3/services/__init__.py
g3/services/generate/__init__.py
g3/services/generate/client.py
g3/services/generate/commit/__init__.py
g3/services/generate/commit/messages/__init__.py
g3/services/generate/commit/messages/creator.py
g3/services/generate/commit/prompts/__init__.py
g3/services/generate/commit/prompts/creator.py
g3/services/generate/commit/prompts/exceptions.py
g3/services/generate/pr/__init__.py
g3/services/generate/pr/messages/__init__.py
g3/services/generate/pr/messages/creator.py
g3/services/generate/pr/prompts/__init__.py
g3/services/generate/pr/prompts/creator.py
g3/services/generate/pr/prompts/template.py
g3/services/generate/preview/__init__.py
g3/services/generate/preview/cli.py
g3/services/git/__init__.py
g3/services/git/client.py
g3/services/git/gitinfo.py
g3/services/git/shell.py
g3/services/github/__init__.py
g3/services/github/client.py
g3/services/github/github_info.py
g3/utils/__init__.py
g3/utils/context_managers.py
g3/utils/dictionary.py
g3-0.5.0.dist-info/LICENSE
g3-0.5.0.dist-info/METADATA
g3-0.5.0.dist-info/WHEEL
g3-0.5.0.dist-info/entry_points.txt
g3-0.5.0.dist-info/RECORD
