Metadata-Version: 2.1
Name: g3
Version: 0.5.0
Summary: An AI-powered CLI tool to help you write better commit messages and PRs.
Author: Panos Antonakos
Author-email: antonakos@workable.com
Requires-Python: >=3.11,<4.0
Classifier: Programming Language :: Python :: 3
Classifier: Programming Language :: Python :: 3.11
Requires-Dist: asyncio (>=3.4.3,<4.0.0)
Requires-Dist: inquirer (>=3.1.3,<4.0.0)
Requires-Dist: openai (>=0.27.8,<0.28.0)
Requires-Dist: pydantic[dotenv] (>=v1.10.10,<2.0.0)
Requires-Dist: pygithub (>=1.59.0,<2.0.0)
Requires-Dist: pyperclip (>=1.8.2,<2.0.0)
Requires-Dist: tiktoken (>=0.4.0,<0.5.0)
Requires-Dist: typer[all] (>=0.9.0,<0.10.0)
